MANIFEST.in
README.md
setup.py
terraform_binary_wrapper/__init__.py
terraform_binary_wrapper.egg-info/PKG-INFO
terraform_binary_wrapper.egg-info/SOURCES.txt
terraform_binary_wrapper.egg-info/dependency_links.txt
terraform_binary_wrapper.egg-info/entry_points.txt
terraform_binary_wrapper.egg-info/top_level.txt
terraform_binary_wrapper/lib/__init__.py
terraform_binary_wrapper/lib/terraform