Metadata-Version: 1.0
Name: terraform-binary-wrapper
Version: 1.0.3.post3
Summary: Python wrapper for Terraform
Home-page: https://github.com/imanazari70/terraform-binary-wrapper
Author: Iman Azari
Author-email: azari@mahsan.co
License: UNKNOWN
Platform: UNKNOWN
